LICENSE
MANIFEST.in
README.md
package.json
setup.py
pagenotfound_threejs/PagenotfoundThreejs.py
pagenotfound_threejs/__init__.py
pagenotfound_threejs/_imports_.py
pagenotfound_threejs/metadata.json
pagenotfound_threejs/package-info.json
pagenotfound_threejs/pagenotfound_threejs.min.js
pagenotfound_threejs/pagenotfound_threejs.min.js.map
pagenotfound_threejs.egg-info/PKG-INFO
pagenotfound_threejs.egg-info/SOURCES.txt
pagenotfound_threejs.egg-info/dependency_links.txt
pagenotfound_threejs.egg-info/top_level.txt