Metadata-Version: 2.1
Name: pagenotfound-threejs
Version: 0.0.1
Summary: Page not found 404 component for python Dash
Home-page: UNKNOWN
Author: Ben Cannell <bean.can.design@gmail.com>
License: GPL-3.0
Platform: UNKNOWN
Classifier: Framework :: Dash
License-File: LICENSE
